dbtogo/__init__.py
dbtogo/datatypes.py
dbtogo/dbmodel.py
dbtogo/exceptions.py
dbtogo/migrations.py
dbtogo/serialization.py
dbtogo/sqlite.py
dbtogo-0.0.5.dist-info/METADATA
dbtogo-0.0.5.dist-info/WHEEL
dbtogo-0.0.5.dist-info/licenses/LICENSE
dbtogo-0.0.5.dist-info/RECORD
