Metadata-Version: 2.4
Name: dbtogo
Version: 0.0.5
Summary: Python ORM on top of Pydantic models with focus on simplicity
Project-URL: Homepage, https://github.com/Graph3x/dbtogo
Project-URL: Issues, https://github.com/Graph3x/dbtogo/issues
Author-email: Filip Hejzlar <hejzlar.filip@seznam.cz>
License-Expression: MIT
License-File: LICENSE
Classifier: Operating System :: OS Independent
Classifier: Programming Language :: Python :: 3
Requires-Python: >=3.12
Requires-Dist: pydantic>=2.0
Provides-Extra: dev
Requires-Dist: mypy; extra == 'dev'
Requires-Dist: pytest; extra == 'dev'
Requires-Dist: pytest-cov; extra == 'dev'
Requires-Dist: ruff; extra == 'dev'
